indomee/__init__.py
indomee/bootstrap.py
indomee/metrics.py
indomee/t_test.py
indomee-0.1.5.dist-info/METADATA
indomee-0.1.5.dist-info/WHEEL
indomee-0.1.5.dist-info/RECORD
