Metadata-Version: 2.4
Name: indomee
Version: 0.1.5
Summary: Python package for evaluation of retrieval-augmented generation (RAG) models
Author-email: Ivan Leo <ivanleomk@gmail.com>
License: MIT
Requires-Python: >=3.11
Requires-Dist: pandas>=2.2.3
Requires-Dist: rich>=13.9.4
Requires-Dist: scipy>=1.14.1
Provides-Extra: dev
Requires-Dist: pre-commit>=4.0.1; extra == 'dev'
Provides-Extra: test
Requires-Dist: pytest>=8.3.3; extra == 'test'
